{"language": "nl_BE", "client_reference": "NSN202010041", "mail_subject": "MISSION_ASSIGNEMENT: NSN20201004103", "mail_content": "in bijlage <anon> wij een document met betrekking tot een opdracht dat toevertrouwd werd in het <anon> <policy_holder_name> de verdediging <policy_holder_name> onze belangen. the present electronic message and all the information it <anon> inclusive of any <anon> document are <anon> confidential and are <anon> <anon> for the <anon> if you are not an <anon> <anon> you must not open use duplicate this message nor <anon> the contents to any third party if the case would happen we <anon> invite you to destroy the present e-mail and to inform the <anon> at once. total safety confidentiality and <anon> of electronic messages can by no means be <anon> the <anon> can <anon> not be held <anon> for damage <anon> <anon> the use of e-mail such as virus contamination and interception or <anon> of transmissions.", "party_id": 21955048183443173, "party_type": "nonNaturalPerson", "unit_id": null, "organization": "Allianz", "from_mail": "NoReplyECNM@allianz.be", "comments": "", "attachments": [{"filename": "MISSION_ASSIGNEMENT.pdf", "content": "<anon> <anon> nv koning <anon> <anon> <number> <number> <anon> <anon> <anon> <number> <number> <anon> <anon> bic: <anon> btw: be <number> <anon> <anon> <anon> verzekeringsmaatschappij toegelaten door <anon> nbb <anon> bank <anon> <anon> onder codenummer <number> om alle <anon> <anon> en <anon> te beoefenen <anon> de <anon> <number> <number> <anon> <anon> <anon> <anon> experts <anon> <anon> <number> <number> sint stevens <anon> <anon> <number> <anon> <number> uw contact: <anon> <anon> <anon> e-mail: <email> <anon> <anon> <anon> <anon> <anon> onze referte: <anon> opdracht: expertise materieel waterschade beste medewerker betreft een expertise met betrekking tot het <anon> <policy_holder_name> <date>. onze verzekerde: van de <policy_holder_name> adres verzekerde: <policy_holder_street> <anon> sint <anon> <anon> ligging risico: niet van toepassing ligging schade: <policy_holder_street> <number> sint <anon> westr contract <anon> schade nummer: <anon> type contract: brand woning makelaar: <anon> bank <anon> <phone> <email> in het <anon> van deze opdracht vragen wij het volgende: onderzoeken van oorzaak en omstandigheden evaluatie van de schade foto's nemen advies <anon> van toepassing voor deze opdracht: van de <policy_holder_name> <policy_holder_name> <anon> <number> <number> sint <anon> <anon> graag dringend afspraak aub verschillende oorzaken <anon> <anon> probleem met douche lek in tuinhuis <anon> bijgevoegd vindt bijkomende informatie aangaande het <anon> we ontvangen graag de bevestiging van uw aanvaarding van deze opdracht tegen <date> als nog vragen heeft aarzel dan niet om ons te contacteren. met vriendelijke groeten <anon> <anon> non motor <anon> bescherming van persoonsgegevens <anon> <anon> verzamelt persoonsgegevens om <anon> op te stellen te beheren en uit te voeren wij gebruiken die gegevens in het bijzonder in het <anon> van de relaties met onze partners en voor specifieke doeleinden de persoonsgegevens worden verwerkt in overeenstemming met de wetgeving inzake de bescherming van persoonsgegevens en de wetten die van toepassing zijn op verzekeringen die gegevens worden met gedeeld voor zover ze absoluut nodig hebt om de opdracht uit te voeren die <anon> toevertrouwt <anon> verwacht van zijn partners dat zij <anon> toepassen die in overeenstemming zijn met de professionele goede praktijken de gegevens mogen in geen geval worden gebruikt voor andere doeleinden dan die van de opdracht noch langer worden bewaard dan noodzakelijk voor de verwerking of dan wettelijk vereist na die periode moet de gegevens teruggeven aan de maatschappij of ze vernietigen meer uitleg over ons beleid inzake de bescherming van persoonsgegevens vindt op onze website: <anon> <anon>", "classification": "NewAssignment", "description": "Nouvelle mission", "language": "Dutch"}, {"filename": "lek tuinhuis foto 1.pdf", "content": "", "classification": "Photo", "description": "Photo", "language": "Dutch"}, {"filename": "Offerte gevolgschade 1.328 \u20ac.pdf", "content": "naam: dhr <anon> adres: <anon> <number> <number> <anon> <anon> <anon> datum: <date> <anon> <number> datum <anon> <anon> <anon> naam: dhr <policy_holder_name> adres: <policy_holder_street> <number> <anon> tel: fax: <anon> e-mail: <anon> firma: btw: omschrijving <anon> totaal overeenkomst voor het injecteren <policy_holder_name> de muren tegen opstijgend vocht afkappen <anon> hoogte <number> cm <number> <number> <anon> behandeling: <anon> hoogte <number> cm <number> <number> <anon> hoogte <number> cm <anon> <anon> <number> <number> <anon> <number> <money> vervangen <anon> plint <number> <anon> <number> lm verven muur <number> <anon> <number> <anon> herstellen <anon> na lek aan <anon> <number> btw <number> indien de aanwezigheid van <anon> zouten <anon> sulfaten <anon> werd vastgesteld is een <anon> behandeling noodzakelijk <anon> dit niet gebeurt bestaat de kans dat de zouten op termijn schade veroorzaken aan <anon> <anon> behang verf <number> de factuur wordt opgemaakt bij be\u00ebindiging van de werken en is onmiddellijk opeisbaar. <number> <anon> bvba verbindt zich ertoe de werken uit te voeren op voorwaarde dat uit het technische verslag geen technische moeilijkheid blijkt die het evenwicht van de overeenkomst wijzigt <number> de klant verklaart <anon> genomen te hebben van de algemene voorwaarden zie achterzijde. <number> <number> maanden na het uitvoeren van de werken is er een gratis nacontrole mogelijk op eenvoudig verzoek van de klant <anon> bvba verbindt zich ertoe de muren te behandelen om de vochtigheid ten gevolge van opstijgend vocht te verminderen met uitsluiting van oppervlakkige <anon> derwijze dat de vochtigheidsgraad boven de <anon> hindernis <anon> dan <number> bedraagt de vochtigheid zal gemeten worden volgens de methode van de <anon> die bestaat uit een <anon> van de <anon> uit de muur op <number> cm diepte en uit een <anon> de oppervlakkige <anon> buiten beschouwing gelaten geen ander <anon> zal in aanmerking komen. <number> tenzij anders vermeld is er voor alle <anon> die door onze diensten werden uitgevoerd een <anon> van <number> jaar beperkt tot de <anon> van de door ons uitgevoerde werken en waar het vochtgehalte ten gevolge van opstijgend vocht hoger is dan <number> ook andere <anon> kunnen het vochtgehalte in de muren be\u00efnvloeden zoals o.a de aanwezigheid van <anon> zouten andere werken deze dan <anon> vallen onder de <anon> van <number> jaar. <number> de werken worden uitgevoerd volgens: de technische <anon> wtcb <anon> <anon> <number> voorschriften van de fabrikant <anon> leverancier van de producten. de samenvattende <anon> en de checklist van de uit te voeren werken. <number> de klant staat zelf in voor de voorbereidende werken zoals het aanduiden van alle leidingen het verwijderen en terugplaatsen van radiatoren elektrische installaties <anon> enz niet uitgevoerde voorbereidende werken zullen supplementair in uurloon worden gefactureerd er wordt door de klant een min werkruimte gecre\u00eberd van <number> meter. algemene <anon> op pagina <number> bestelbon <anon> <number> <money> <number> <money> <number> <money> totaal te betalen klant erkent een exemplaar ontvangen te hebben en tekent voor akkoord <anon> <anon> algemene <anon> <number> deze overeenkomst is onderworpen aan de bepalingen van <anon> iii uit boek iii van het burgerlijk wetboek <anon> en verbintenissen uit overeenkomst in het algemeen) en meer bepaald door artikels <number> tot <number> daarvan <anon> en <anon> en de wet van <number> juli <number> op de <anon> en op de informatie en de verdediging van de gebruiker <number> onze offerte verbindt <anon> bvba gedurende <number> <anon> <number> door zijn bestelling aanvaardt de klant de toepassing van de algemene voorwaarden van <anon> bvba met uitsluiting van <anon> andere bepaling waarmee <anon> bvba zich niet uitdrukkelijk en schriftelijk akkoord heeft verklaard <number> de werken worden uitgevoerd volgens de <anon> in geval van tegenstrijdigheid tussen de <anon> zal de voorrang gelden in deze volgorde: het contract en de algemene voorwaarden van <anon> bvba de plannen het bestek de <anon> wanneer deze documenten interne tegenstrijdigheden bevatten mag <anon> bvba laten gelden dat hij de voor haar meest gunstige hypothese heeft voorzien <number> de prijzen zijn vast en niet <anon> gedurende drie maanden na de datum waarop deze overeenkomst ondertekend wordt behoudens bijzondere bedingen opgenomen in het vak gebeurlijke bijzondere voorwaarden als die termijn verstreken is zal de prijs worden aangepast volgens de <anon> van het bouwbedrijf <number> <anon> bvba zal niet gehouden zijn deze overeenkomst uit te voeren in geval van overmacht of in geval van vreemde oorzaak die aan overmacht is toegeschreven of ermede gelijkgesteld kan worden zoals ongeval aan de <anon> brand <anon> opeisen door het leger <anon> staking van haar personeel of dat van haar leveranciers of van de installateur lock-out technische werkloosheid epidemie gebrek of schaarste van grondstoffen of van vervoermiddelen overstroming of alle andere moeilijkheden in de <anon> <number> <anon> bvba behoudt zich het recht voor het ontwerp en het bestek van <anon> installatie te wijzigen indien dat nodig blijkt om de in deze overeenkomst bedongen behandeling tot een goed einde te brengen <number> de klant verbindt zich de afgevaardigden en beambten van <anon> bvba en onderaannemers vrije toegang tot de lokalen te verlenen telkens als dat nodig zal zijn voor de nodige <anon> en om de werken tot een goed einde te brengen <number> indien <anon> bvba en onderaannemers om een of andere reden geen toegang krijgen tot de lokalen op de onder de partijen afgesproken dag en uur zal de klant haar de kosten moeten vergoeden die door de nutteloze reis teweeggebracht zijn <number> de klant zal <anon> bvba en onderaannemers de voor de werken nodige electriciteit en water kosteloos verschaffen <number> a) <anon> bvba behoudt zich het recht voor deze overeenkomst geheel of gedeeltelijk op te zeggen ingeval in een of ander stadium <anon> of na het begin van de werken) de structuur van de lokalen ongeschikt zou blijken voor de toepassing der <anon> bvbas <anon> of indien het onmogelijk zou blijken een of ander deel van die structuur volkomen veilig te bereiken met behulp van de door <anon> bvba normaal gebruikte uitrusting ingeval de in dit lid bedongen <anon> na het begin der werken gebruikt wordt zal <anon> bvba haar best doen om voor zover zij hiertoe in staat is de schade te herstellen die door de <anon> uitgevoerde werken veroorzaakt mocht zijn b) indien de overeenkomst echter slechts gedeeltelijk uitgevoerd is zal aan <anon> bvba een gedeelte van de overeengekomen prijs toekomen in verhouding tot de werkelijk uitgevoerde werken <number> <anon> bvba kan niet aansprakelijk worden gesteld voor de detectie van de <anon> en het lokaliseren van de <anon> van het vocht mocht blijken dat er uiteindelijk nog andere <anon> zorgen voor <anon> dan is dit geen reden om de verbintenissen ten aanzien van <anon> bvba te verbreken of niet verder na te komen <number> <anon> bvba zal alle nodige voorzorgsmaatregelen nemen om te vermijden dat ze tijdens de werken schade aanricht aan de <anon> van de lokalen maar voor onvermijdelijke schade kan ze niet instaan <anon> klacht van de klant over de uitvoering van de werken door <anon> bvba of door de onderaannemers van <anon> bvba moet op straffe van verval binnen de acht dagen na het verweten <anon> en in ieder geval v\u00f3\u00f3r de <anon> ingediend worden <anon> bvba is niet verantwoordelijk voor <anon> vorm van beschadiging aan kabels leidingen of onzichtbare voorwerpen in de te behandelen delen van het gebouw als de bouwheer voor aanvang van de werken niet op de aanwezigheid van deze elementen heeft gewezen <anon> bvba is ook niet verantwoordelijk voor <anon> die veroorzaakt worden door een <anon> <anon> en door fenomenen veroorzaakt door <anon> zouten <anon> bvba is niet verantwoordelijk voor schade aan de werken toegebracht door externe oorzaken zoals graafwerken <anon> en <anon> van het gebouw) hierdoor kunnen <anon> ontstaan die <anon> tot gevolg kunnen hebben <number> de klant is tegenover derden en in <anon> tegenover zijn <anon> volledig aansprakelijk voor schade die het onvermijdelijk gevolg is van de uitvoering van de werken wanneer de aannemer geen enkele fout kan worden <anon> <number> bij het einde van de werken zal een proces-verbaal van <anon> van de werken worden opgemaakt en door de klant en de firma ondertekend worden in ieder geval indien er geen proces-verbaal van de <anon> ondertekend wordt zal het onder voorbehoud betalen der factuur als <anon> van <anon> gelden <number> de klant bevestigt dat hij eigenaar of mede-eigenaar is van het te behandelen gebouw of dat hij door de eigenaar of mede-eigenaar van dat gebouw gemachtigd is en dat hij in die hoedanigheid alle macht heeft om met betrekking tot zijn in deze overeenkomst <anon> verbintenissen daarover te beslissen en die aan te gaan <number> de betaling der werken zal eisbaar zijn op het tijdstip van de voltooiing daarvan hetzij in baar geld hetzij met overschrijving bij betaling in baar geld zal de klant de betaling verrichten in de handen van de gemachtigde afgevaardigden en beambten van <anon> bvba de klant moet een exemplaar der overeenkomst bewaren waarop het betrokken bedrag vermeld staat en die voor kwijting ondertekend is door de afgevaardigde die de betaling ontvangen heeft <number> gelet op de bestaande beschrijvende documentatie die door <anon> bvba uitgegeven is en die de karakteristieken alsmede de <anon> van het systeem van <anon> bvba beschrijft zal <anon> bijkomende bepaling die niet geschreven en door een bestuurder van <anon> bvba ondertekend is als niet bestaand beschouwd worden <number> de klant mag niet <anon> dat <anon> bvba werken uitvoert of materialen <anon> die in deze overeenkomst niet bedongen zijn <number> zolang de prijs niet volledig betaald is zal <anon> bvba volledig eigenaar blijven van het geleverde materiaal dat niet ingelijfd is in het gebouw waarvan sprake in de in de overeenkomst <anon> bestelling <number> elk bedrag dat op de vervaldag door de klant niet betaald is zal het voordeel van de betalingstermijn verbeuren en de schuld eisbaar maken die schuld zal van <anon> en zonder <anon> rente opleveren aan <number> per maand onafhankelijk van deze rente komen de partijen uitdrukkelijk overeen dat het niet betalen van \u00e9\u00e9n factuur op de vervaldatum volgende kosten aangerekend worden en verschuldigd zijn: <number>e <anon> <money> <number> <anon> <number>e aangetekende <anon> <money> <anon> wanneer dossier ter incasso wordt uitgegeven: een forfaitaire schadevergoeding gelijk aan <number> berekend op het verschuldigd <anon> met een minimum van <money> <number> ingeval de klant de overeenkomst eenzijdig verbreekt of ingeval hij bij een ontbinding der overeenkomst in het ongelijk is zal hij de overeengekomen prijs schuldig zijn in verhouding tot de <anon> uitgevoerde werken alsmede een schadevergoeding gelijk aan <number> van de overeengekomen waarde der niet uitgevoerde werken btw inbegrepen <number> <anon> bvba waarborgt haar werk en de producten onder de voorwaarden en voor de duur die bepaald zijn in het <anon> waarvan de klant een ondertekend exemplaar ontvangen zal nadat ieder krachtens de overeenkomst verschuldigd bedrag volledig betaald is deze overeengekomen waarborg begint te lopen vanaf de dag waarop de werken voltooid zijn de klant zal het voordeel van die waarborg <anon> kunnen inroepen nadat het krachtens de overeenkomst verschuldigde bedrag volledig betaald is <number> de bedingen van het tussen <anon> bvba en de klant bereikte akkoord zijn volledig in deze overeenkomst vervat die door beide partijen ondertekend moet worden <number> bij eventuele <anon> ivm de uitvoering van deze overeenkomst zijn uitsluitend de rechtbanken van de zetel van de aannemer bevoegd nl de rechtbanken van gent <anon> het belgische recht is van toepassing", "classification": "Quotation", "description": "Offre", "language": "Dutch"}, {"filename": "rapport Cibor.pdf", "content": "opdrachtgever <anon> <anon> <policy_holder_name> <policy_holder_street> <number> <anon> <anon> belgi\u00eb <anon> <policy_holder_name> de <policy_holder_name> <policy_holder_street> <number> <anon> belgi\u00eb t: <anon> <anon> datum <anon> start start vanaf <number>: <number>u <anon> <anon> <anon> <anon> dossiernummer: <number> beheerder jan werkbon nr <number> <anon> klant dossiernummer: <anon> <anon> referentie <anon> rapport <anon> <date> <anon> <anon> verkregen voorafgaand aan onze interventie) het betreft het opsporen van een waterlek in een vrijstaande woning met zichtbare schade aan de muren van de <anon> de watermeter werd gecontroleerd en er werd een heel licht verlies vastgesteld technieken manometer <anon> <anon> <anon> foto's <anon> <anon> nv <anon> <number> <number> <anon> <anon> <email> tel <anon> <anon> div <anon> <anon> <anon> <anon> div <anon> <anon> <anon> <anon> <anon> controle van de <anon> de klant verklaart geen drukverlies te hebben op centrale verwarming <anon> drukverlies: verlies op waterleiding niet geweten ja nee grootte drukverlies: types verlies koud warm vaststellingen <anon> het betreft een vrijstaande woning er is een lekkage op de waterleidingen in de <anon> op de eerste verdieping geweest er is zichtbare <anon> in de slaapkamer op de <anon> met de badkamer waar de <anon> staat er is geen <anon> op het gelijkvloers geweest de waterleiding in de <anon> werd hersteld de verzekerde heeft nog steeds een klein verlies op de <anon> vastgesteld. inspectie: de waterleiding in de douche werd een week geleden hersteld de <anon> van de douche is nog steeds bloot de herstelling is nog zichtbaar <anon> <number>) de verzekerde heeft de oude stukken waar een lekkage was bewaard <anon> foto's <number> en <number>) met de <anon> werden waar de <anon> zichtbaar is <anon> <anon> vastgesteld <anon> <number> en <number>) de watermeter staat vooraan de oprit waar een <anon> naar de woning gaat in de woning kan de waterleiding ook worden afgesloten met de manometer werd op de waterleiding buiten de woning een <anon> uitgevoerd zonder een verlies vast te stellen met de manometer werd op de waterleiding een <anon> uitgevoerd <anon> in de woning werd een klein verlies vastgesteld in de berging vertrekken <anon> vanuit de collectoren naar de verschillende <anon> zonder <anon> er is <anon> een kraan naar het circuit van boven er is geen verlies op de eerste verdieping de <anon> mag dus worden hersteld er is geen <anon> te horen. conclusies de waterleiding in de <anon> werd hersteld er is nog steeds zichtbare <anon> in de slaapkamer maar dit is nog <anon> <anon> een week hersteld) er is geen verlies op de waterleidingen op de eerste verdieping de <anon> mag worden hersteld <anon> er is geen verlies op de <anon> buiten de woning er is een verlies op de waterleiding in de woning we hebben nog geen duidelijke plaats van het lek kunnen aantonen met de beschikbare <anon> we hebben aan de verzekerde voorgesteld om <anon> op de <anon> te plaatsen zodat kan bepaald worden in welke zone het lek zich moet situeren de <anon> zijn niet traceerbaar met de <anon> en er is verder nergens schade vast te stellen er is na het plaatsen van de <anon> een bijkomende interventie nodig. <anon> <anon> nv <anon> <number> <number> <anon> <anon> <email> tel <anon> <anon> div <anon> <anon> <anon> <anon> div <anon> <anon> <anon> <anon> <anon> <anon> <anon> <anon> rapport <anon> foto <number>: vrijstaande woning foto <number>: douche werd deels uitgebroken en het lek werd hersteld <anon> <anon> nv <anon> <number> <number> <anon> <anon> <email> tel <anon> <anon> div <anon> <anon> <anon> <anon> div <anon> <anon> <anon> <anon> <anon> <anon> <anon> <anon> rapport <anon> foto <number> foto <number> <anon> <anon> nv <anon> <number> <number> <anon> <anon> <email> tel <anon> <anon> div <anon> <anon> <anon> <anon> div <anon> <anon> <anon> <anon> <anon> <anon> <anon> <anon> rapport <anon> foto <number> foto <number>: <anon> in de slaapkamer <anon> <anon> nv <anon> <number> <number> <anon> <anon> <email> tel <anon> <anon> div <anon> <anon> <anon> <anon> div <anon> <anon> <anon> <anon> <anon> <anon> <anon> <anon> rapport <anon> foto <number> foto <number> <anon> <anon> nv <anon> <number> <number> <anon> <anon> <email> tel <anon> <anon> div <anon> <anon> <anon> <anon> div <anon> <anon> <anon> <anon> <anon> <anon> <anon> <anon> rapport <anon> foto <number> foto <number> <anon> <anon> nv <anon> <number> <number> <anon> <anon> <email> tel <anon> <anon> div <anon> <anon> <anon> <anon> div <anon> <anon> <anon> <anon> <anon> <anon> <anon> <anon> rapport <anon> foto <number> foto <number>: <anon> <anon> <anon> nv <anon> <number> <number> <anon> <anon> <email> tel <anon> <anon> div <anon> <anon> <anon> <anon> div <anon> <anon> <anon> <anon> <anon> <anon> <anon> <anon> rapport <anon> foto <number>: <anon> op de waterleiding buiten de woning: geen verlies foto <number> <anon> <anon> nv <anon> <number> <number> <anon> <anon> <email> tel <anon> <anon> div <anon> <anon> <anon> <anon> div <anon> <anon> <anon> <anon> <anon> <anon> <anon> <anon> rapport <anon> foto <number> foto <number> <anon> <anon> nv <anon> <number> <number> <anon> <anon> <email> tel <anon> <anon> div <anon> <anon> <anon> <anon> div <anon> <anon> <anon> <anon> <anon> <anon> <anon> <anon> rapport <anon> foto <number> foto <number> <anon> <anon> nv <anon> <number> <number> <anon> <anon> <email> tel <anon> <anon> div <anon> <anon> <anon> <anon> div <anon> <anon> <anon> <anon> <anon> <anon> <anon> <anon> rapport <anon> foto <number> foto <number>: <anon> op de waterleidingen toont een klein verlies aan <anon> <anon> nv <anon> <number> <number> <anon> <anon> <email> tel <anon> <anon> div <anon> <anon> <anon> <anon> div <anon> <anon> <anon> <anon> <anon> <anon> <anon> <anon> rapport <anon> foto <number> foto <number> <anon> <anon> nv <anon> <number> <number> <anon> <anon> <email> tel <anon> <anon> div <anon> <anon> <anon> <anon> div <anon> <anon> <anon> <anon> <anon> <anon> <anon> <anon> rapport <anon> foto <number> foto <number> <anon> <anon> nv <anon> <number> <number> <anon> <anon> <email> tel <anon> <anon> div <anon> <anon> <anon> <anon> div <anon> <anon> <anon> <anon> <anon> <anon> <anon> <anon> rapport <anon> foto <number>: plaats waar <anon> mogen worden geplaatst foto <number>: werkbon <number> <anon> <anon> nv <anon> <number> <number> <anon> <anon> <email> tel <anon> <anon> div <anon> <anon> <anon> <anon> div <anon> <anon> <anon> <anon> ul <anon> <anon> <anon> <anon> ul <anon> <anon> <anon> <anon> <anon> <anon> <anon> <anon> <anon> verkregen voorafgaand aan onze <anon> <anon> <anon> van de <anon> <anon> <anon> <anon> <anon> <anon> rapport <anon> <anon> <anon> <anon> rapport <anon> <anon> <anon> <anon> rapport <anon> <anon> <anon> <anon> rapport <anon> <anon> <anon> <anon> rapport <anon> <anon> <anon> <anon> rapport <anon> <anon> <anon> <anon> rapport <anon> <anon> <anon> <anon> rapport <anon> <anon> <anon> <anon> rapport <anon> <anon> <anon> <anon> rapport <anon> <anon> <anon> <anon> rapport <anon> <anon> <anon> <anon> rapport <anon> <anon> <anon> <anon> rapport <anon> <anon> <anon>", "classification": "LeakDetectionReport", "description": "Rapport de d\u00e9tection de fuite", "language": "Dutch"}, {"filename": "factuur Hendrickx 960,36 \u20ac.pdf", "content": "", "classification": "Dummy", "description": "", "language": "Dutch"}, {"filename": "factuur 1 Cibor 405 \u20ac.pdf", "content": "", "classification": "Invoice", "description": "Facture", "language": "Dutch"}, {"filename": "facture.pdf", "content": "", "classification": "Invoice", "description": "Facture", "language": "Dutch"}, {"filename": "aangifte schadegeval.pdf", "content": "from: heye <anon> date: <number> september <number> <number>: <number> to: <email> subject: aangifte <anon> beste hierbij in bijlage aangifte <anon> <anon> voor polis <anon> mensen stellen vast dat de muur in hun slaapkamer <anon> vertoond <anon> fotos in <anon> op <date> is firma <anon> d&d bvba bij de klant langs geweest voor het <anon> <policy_holder_name> de voegen van de douche. omdat het probleem hiermee niet bleek opgelost te zijn is de firma vandaag <date> opnieuw langsgekomen voor het uitbreken van de tegels aan de achterwand van de douche. daarbij is vastgesteld dat er effectief vocht te zien is ter hoogte van de leidingen van de <anon> daarop is loodgieter msm bvba langsgekomen bij de klant <anon> bijlage) zij hebben het lek vastgesteld ter hoogte van de koppeling van de kraan en deze vervangen in de hoop dat dit het enige lek was. de klant volgt het <anon> op als er deze nacht water zou verbruikt zijn <anon> dat ze hiervan effectief gebruik gemaakt hebben) dan weten we jammer genoeg dat er nog ergens anders een lek is. dit is de voorlopige stand van zaken wij houden verder op de hoogte van ontwikkelingen. in bijlage: fotos van de betreffende muur in de slaapkamer fotos van de douche voor de werken fotos van de douche nadat de tegels aan de achterwand werden uitgebroken fotos van de leidingen met daarop duidelijke <anon> foto van het koppelstuk dat werd verwijderd en vervangen waarop duidelijk te zien is dat dit voor <anon> <anon> vertoond van het sijpelende water offerte voor het herstellen van de <anon> aan de achterwand van de douche aankoop van de tegels voor de achterwand van de douche nog te verwachten: offerte herstelling schilderwerken muur slaapkamer factuur <number>e <anon> uitbreken tegels achterwand douche <anon> door firma <anon> d&d bvba) in het slechtste geval blijkt de oorzaak niet te zijn weggenomen door het herstel dan volgt uiteraard verder communicatie. graag dringend opvolgen <anon> werd nog niet hersteld om eventueel expertise toe te staan. vriendelijke groeten <anon> heye <anon> <anon> <anon> <anon> <email> <email> <anon> <anon> bank nv <anon> <anon> <anon> <number> <anon> mail disclaimer <anon> general e-mail information: from heye <anon> <anon> to <email> <anon> <anon> <anon> <anon> <email> <anon> subject aangifte <anon> date <date> <number>: <number>: <number> <anon> <anon> of categories <anon> <anon> <anon> <number>a <anon> <number>a offerte plaatsten nieuwe tegels douche <anon> <anon> <anon> <number>a aankoop tegels <anon> <number>a werkbon loodgieter msm <anon> <number>a <anon> description <number>a these documents are <anon> to pdf <number>b these documents are <anon> to pdf the original file is also <anon> to the pdf <number>a these documents are <anon> in original format <number>b container page is <anon> and the original file is <anon> to the container pdf <number> these documents are <anon>", "classification": "Statement", "description": "D\u00e9claration", "language": "Dutch"}, {"filename": "rapport Cibor 2 - probleem leiding tuinhuis en wasverzachter.pdf", "content": "opdrachtgever <anon> <anon> <policy_holder_name> <policy_holder_street> <number> <anon> <anon> belgi\u00eb <anon> <policy_holder_name> de <policy_holder_name> <policy_holder_street> <number> <anon> belgi\u00eb t: <anon> <anon> datum <anon> start start vanaf <number>: <number>u <anon> <anon> <anon> <anon> dossiernummer: <number> beheerder jan werkbon nr <number> <anon> klant dossiernummer: <anon> <anon> referentie <anon> rapport <anon> bijkomende interventie van dossier <number> <date> <anon> <anon> verkregen voorafgaand aan onze interventie) de <anon> zijn geplaatst dus er kan een bijkomend onderzoek worden uitgevoerd. technieken manometer <anon> <anon> <anon> <anon> foto's <anon> <anon> nv <anon> <number> <number> <anon> <anon> <email> tel <anon> <anon> div <anon> <anon> <anon> <anon> div <anon> <anon> <anon> <anon> <anon> controle van de <anon> de klant verklaart geen drukverlies te hebben op centrale verwarming <anon> drukverlies: niet van toepassing verlies op waterleiding niet geweten ja nee grootte drukverlies: types verlies koud warm vaststellingen <anon> het betreft een bijkomende interventie van dossier <number> op de aangeduide plaats werden afsluiters geplaatst. inspectie: met de manometer wordt op de waterleidingen een drukproef uitgevoerd en er wordt vastgesteld dat er een verlies op de <anon> is na het sluiten van de <anon> wordt op de <anon> geen verlies meer vastgesteld een bijkomende drukproef op de <anon> toont een verlies aan op de <anon> die naar het tuinhuis gaat in de <anon> wordt <anon> geplaatst en er wordt in het tuinhuis lichtjes gas gemeten met de <anon> is geen <anon> te horen. conclusies tijdens de bijkomende drukproef op de waterleidingen wordt vastgesteld dat er een verlies op de <anon> is na het sluiten van de <anon> wordt op de <anon> geen verlies meer vastgesteld een bijkomende drukproef op de <anon> toont een verlies op de <anon> die naar het tuinhuis gaat er werd in de waterleiding <anon> geplaatst en er werd gas in het tuinhuis gemeten de vermoedelijke plaats werd aan de verzekerde getoond er werd aan de verzekerde uitgelegd dat de aangeduide plaats kan afwijken omdat de <anon> in een <anon> zit de verzekerde gaat op de aangeduide plaats <number> tegel verwijderen. <anon> <anon> nv <anon> <number> <number> <anon> <anon> <email> tel <anon> <anon> div <anon> <anon> <anon> <anon> div <anon> <anon> <anon> <anon> <anon> <anon> <anon> <anon> rapport <anon> foto <number> foto <number> <anon> <anon> nv <anon> <number> <number> <anon> <anon> <email> tel <anon> <anon> div <anon> <anon> <anon> <anon> div <anon> <anon> <anon> <anon> <anon> <anon> <anon> <anon> rapport <anon> foto <number> foto <number> <anon> <anon> nv <anon> <number> <number> <anon> <anon> <email> tel <anon> <anon> div <anon> <anon> <anon> <anon> div <anon> <anon> <anon> <anon> <anon> <anon> <anon> <anon> rapport <anon> foto <number> foto <number> <anon> <anon> nv <anon> <number> <number> <anon> <anon> <email> tel <anon> <anon> div <anon> <anon> <anon> <anon> div <anon> <anon> <anon> <anon> <anon> <anon> <anon> <anon> rapport <anon> foto <number> foto <number> <anon> <anon> nv <anon> <number> <number> <anon> <anon> <email> tel <anon> <anon> div <anon> <anon> <anon> <anon> div <anon> <anon> <anon> <anon> <anon> <anon> <anon> <anon> rapport <anon> foto <number> foto <number> <anon> <anon> nv <anon> <number> <number> <anon> <anon> <email> tel <anon> <anon> div <anon> <anon> <anon> <anon> div <anon> <anon> <anon> <anon> <anon> <anon> <anon> <anon> rapport <anon> foto <number> foto <number> <anon> <anon> nv <anon> <number> <number> <anon> <anon> <email> tel <anon> <anon> div <anon> <anon> <anon> <anon> div <anon> <anon> <anon> <anon> <anon> <anon> <anon> <anon> rapport <anon> foto <number> foto <number> <anon> <anon> nv <anon> <number> <number> <anon> <anon> <email> tel <anon> <anon> div <anon> <anon> <anon> <anon> div <anon> <anon> <anon> <anon> <anon> <anon> <anon> <anon> rapport <anon> foto <number> <anon> <anon> nv <anon> <number> <number> <anon> <anon> <email> tel <anon> <anon> div <anon> <anon> <anon> <anon> div <anon> <anon> <anon> <anon> ul <anon> <anon> <anon> bijkomende interventie van dossier <number> <anon> ul <anon> <anon> <anon> <anon> <anon> <anon> <anon> <anon> <anon> verkregen voorafgaand aan onze <anon> <anon> <anon> van de <anon> <anon> <anon> <anon> <anon> <anon> rapport <anon> <anon> <anon> <anon> rapport <anon> <anon> <anon> <anon> rapport <anon> <anon> <anon> <anon> rapport <anon> <anon> <anon> <anon> rapport <anon> <anon> <anon> <anon> rapport <anon> <anon> <anon> <anon> rapport <anon> <anon> <anon> <anon> rapport <anon> <anon> <anon>", "classification": "LeakDetectionReport", "description": "Rapport de d\u00e9tection de fuite", "language": "Dutch"}, {"filename": "waterschade Van de Gehuchte-Ballegeer.pdf", "content": "from: <anon> <anon> date: <number> september <number> <number>: <number> to: heye <anon> subject: <anon> <anon> de <anon> beste <anon> in bijlage de offerte <policy_holder_name> <anon> betreft herstelling vocht in muur van kamer naast douche. <anon> komt loodgieter kraantjes plaatsen op <number> leidingen en <anon> kan ik afspraak inplannen terug met <anon> voor <anon> ik hou je verder op de hoogte. mvg <anon> <anon> <anon>", "classification": "Dummy", "description": "", "language": "Dutch"}, {"filename": "Cibor factuur 2 405 \u20ac.pdf", "content": "<anon> omschrijving artikel aantal prijs <anon> <anon> <anon> <policy_holder_name> <policy_holder_street> <anon> <anon> factuur <anon> datum <anon> <anon> <number> <number> <anon> tel: <anon> fax: <anon> <email> <anon> <date> geen <anon> vervaldatum <date> bezoek ons op <anon> <number>/ <number> <anon> <number> <policy_holder_name> <date> <number> opsporen van lekken <anon> interventie) <number> <number> <number> opdracht telefonisch <anon> <date> van de <policy_holder_name> uitvoering onze interventie <anon> <date> <anon> van de gehuchte <policy_holder_street> <number> <anon> polis: <anon> het rapport wordt verstuurd na ontvangst van betaling. <number> <number> <number> totaal exclusief btw in totaal inclusief btw in gestructureerde mededeling: <anon> btw <number> mz <anon> nv <anon> <number> <number> <anon> btw be <number> <anon> <number> <anon> antwerpen afd <anon> op al onze facturen zijn onze algemene <anon> van toepassing <anon> <anon> bnp <anon> <anon> ing <anon> <anon> bic: <anon> <anon> bic: <anon> <anon> bic: <anon> <anon> bic: <anon> bank div <anon> <anon> div <anon> <anon> div <anon>", "classification": "Invoice", "description": "Facture", "language": "Dutch"}, {"filename": "Bestandenblad.pdf", "content": "<date> <anon> <anon> beheerder schade datum nr agt nr polis <anon> <anon> <anon> <date> <number> <anon> <number> <anon> <date> datum schorsing polis financiering <anon> datum vernietig <anon> hypothecaire <anon> getroffen risico nummer: <number> <anon> <anon> agent <number> <policy_holder_name> de <policy_holder_name> <policy_holder_name> <anon> bank <anon> <policy_holder_street> <anon> <number> <number> <anon> <number> <anon> bankrekening <phone> ax referte <anon> regeling via agent regionale zetel <number> historique sinistres montants en eur sinistre gestionnaire lieu gest date cause <anon> r\u00e9serve paiement date rc sinistre <anon> bm si sinistre vol dans les <number> ans appliquer des mesures <anon> koning <anon> <anon> <number> <number> <anon> il <number> <number> <number> <number> <number>z tr <anon> <anon> <anon> nv koning <anon> <anon> <number> <anon> <anon> <anon> <number> <number> <anon> <anon> bic: <anon> btw: be <number> <anon> <anon> <anon> verzekeringsmaatschappij toegelaten door de nbb <anon> bank <policy_holder_name> <anon> onder codenummer <anon> alle <anon> <anon> en <anon> te beoefenen <anon> de <anon> <number> <anon> <anon> bijzondere voorwaarden schade aan particuliere zaken <anon> <anon> uw producent <anon> <number>) de <anon> mevr van de <policy_holder_name> <policy_holder_name> <anon> bank <anon> <anon> <anon> <number> bus <number> <number> <anon> <number> <anon> tel <phone> ref producent <number> brand woning onze referenties <anon> algemene inlichtingen van het contract nr <anon> <anon> <date> splitsing van de premie trimestrieel jaarlijkse vervaldag <anon> einddatum <date> deze <anon> wordt gesloten voor de duur van \u00e9\u00e9n jaar tenzij \u00e9\u00e9n van de partijen er zich ten minste drie maanden voor het einde van de overeenkomst tegen verzet wordt zij stilzwijgend verlengd voor opeenvolgende periodes van \u00e9\u00e9n jaar verzet tegen de stilzwijgende verlenging dient te worden kenbaar gemaakt door middel van een ter post aangetekende brief een <anon> of de aangifte van een <anon> tegen ontvangstbewijs. verzekerd risico nr <number> ligging van het risico <policy_holder_street> <number> <anon> hoedanigheid <anon> eigenaar beschrijving van het risico <anon> verzekerde bedragen en gevaren <anon> <anon> waarborgen verzekerde index jaarlijkse <anon> bedragen premie gebouw <number> <number> <anon> brand storm agel waterschade <anon> burgerlijke aansprakelijkheid natuurrampen inhoud <number> <number> <anon> brand storm agel waterschade <anon> burgerlijke aansprakelijkheid natuurrampen <anon> copij cliche schade nr <anon> koning <anon> <anon> <number> <number> <anon> ln <number> <number> <number> <number> <number>z tr <anon> merk op dat als verschillende <anon> gaat vergelijken niet <anon> de geraamde kosten en lasten van de overeenkomsten met elkaar mag vergelijken maar ook andere elementen in aanmerking moet nemen zoals de reikwijdte van de waarborgen het bedrag van eventuele vrijstellingen of de <anon> de hierboven opgegeven ramingen geven een beter zicht op het <anon> dat wordt aangewend voor de dekking van het risico dat door de <anon> wordt gedekt het <anon> van de premie na aftrek van de taksen en bijdragen alsook van de acquisitie- en <anon> bestaat immers uit het gedeelte van de premie dat wordt aangewend om de contractueel vastgelegde prestaties te verrichten en uit de andere kosten dan hierboven vermeld <anon> de samengevoegde en onderling gedeelde kosten van de <anon> en het beheer <anon> deze ramingen zijn berekend op grond van de boekhoudkundige gegevens van het laatste boekjaar van de <anon> als goedgekeurd door haar algemene vergadering. <anon> <anon> nv koning <anon> <anon> <number> <anon> <anon> <anon> <number> <number> <anon> <anon> bic: <anon> btw: be <number> <anon> <anon> <anon> verzekeringsmaatschappij toegelaten door de nbb <anon> bank van <anon> onder codenummer <anon> alle <anon> <anon> en <anon> te beoefenen <anon> de <anon> <number> <anon> <anon> pagina <number> contract nr <anon> schade <anon> rechtsbijstand geen index <number> <number> <anon> bijzondere clausules met betrekking tot het risico <anon> in bijlage <anon> <anon> <anon> <anon> <anon> <anon> <anon> <anon> <anon> <anon> totale premie voor het contract contante premie premie <anon> <anon> van <date> trimestrieel tot <date> vanaf <date> totale <anon> <anon> <anon> taksen en bijdragen <number> <number> polis- of <anon> totaal te betalen <number> <money> kosten inbegrepen in de <anon> <anon> <number> <number> <anon> <number> <number> bijzondere clausules met betrekking tot het contract <anon> in bijlage <anon> <anon> <anon> <anon> <anon> <anon> <anon> <anon> <anon> <anon> nv koning <anon> <anon> <number> <anon> <anon> <anon> <number> <number> <anon> <anon> bic: <anon> btw: be <number> <anon> <anon> <anon> verzekeringsmaatschappij toegelaten door de nbb <anon> bank van <anon> onder codenummer <anon> alle <anon> <anon> en <anon> te beoefenen <anon> de <anon> <number> <anon> <anon> pagina <number> contract nr <anon> schade <anon> de <anon> verklaart dat hij de algemene voorwaarden ad <number> <anon> op papier of in elektronische vorm heeft ontvangen of op de website <anon> heeft bekeken en de inhoud ervan heeft begrepen. in tweevoud opgemaakt te <anon> op <date>. de <anon> voor de maatschappij <anon> van den <anon> ceo <anon> <anon> <anon> <anon> nv koning <anon> <anon> <number> <anon> <anon> <anon> <number> <number> <anon> <anon> bic: <anon> btw: be <number> <anon> <anon> <anon> verzekeringsmaatschappij toegelaten door de nbb <anon> bank van <anon> onder codenummer <anon> alle <anon> <anon> en <anon> te beoefenen <anon> de <anon> <number> <anon> <anon> pagina <number> contract nr <anon> schade <anon> bijzondere clausules met betrekking tot het contract <anon> dekking van schade veroorzaakt door terrorisme de vergoedingen die in het <anon> van deze <anon> verschuldigd zijn betreffende schade veroorzaakt door terrorisme zijn gewaarborgd binnen het <anon> de perken en de tijdslimieten van de wet van <number> <anon> <number> betreffende de verzekering tegen schade veroorzaakt door terrorisme aangezien <anon> <anon> n.v lid is van trip vzw de rechtspersoon die werd opgericht in uitvoering van de bepalingen van deze wet. schade veroorzaakt door wapens of tuigen die bestemd zijn om te ontploffen door de <anon> van de atoomkern wordt uitgesloten in deze <anon> <anon> economische sancties. het <anon> biedt geen enkele dekking of prestatie voor deze of enige andere verzekering in de mate dat deze dekking of prestatie enige toepasselijke wet sanctie of <anon> van de verenigde naties <anon> de europese unie <anon> om het even welke andere nationale wet of <anon> schendt met betrekking tot economische of commerci\u00eble sancties. <anon> segmentatie onze <anon> hebben een impact gehad op het voorgestelde tarief in de toekomst kunnen deze criteria tevens een rol spelen op de <anon> van het contract meer informatie over onze <anon> op onze website <anon> <anon> uitsluiting <anon> ongeacht de waarborg vergoedt <anon> nooit de schade kosten en verliezen die zelfs gedeeltelijk het gevolg zijn van de aanwezigheid of verspreiding van asbest of <anon> materialen. <anon> <anon> <anon> nv koning <anon> <anon> <number> <anon> <anon> <anon> <number> <number> <anon> <anon> bic: <anon> btw: be <number> <anon> <anon> <anon> verzekeringsmaatschappij toegelaten door de nbb <anon> bank van <anon> onder codenummer <anon> alle <anon> <anon> en <anon> te beoefenen <anon> de <anon> <number> <anon> <anon> pagina <number> contract nr <anon> schade <anon> <anon> <anon> deze <anon> is het resultaat van de exclusieve onderhandelingen tussen <anon> bank en <anon> <anon> de bepalingen en voorwaarden van deze polis staan ter beschikking van de klanten van <anon> bank en zijn bijgevolg exclusief eigendom van <anon> tijdens de volledige duur van het beheer en de polis mag in geen geval gemandateerd worden ten voordele van een andere <anon> indien de <anon> van tussenpersoon wil veranderen moet hij bijgevolg deze overeenkomst opzeggen in de vorm en de termijn die contractueel vastgelegd zijn of voortvloeien uit de wet van <number> <anon> <number> op de verzekeringen <anon> bank behoudt het exclusief recht op het beheer van de overeenkomst en ook het recht op commissies tot de datum waarop de <anon> ingaat datum waarop een nieuwe overeenkomst volgens de bepalingen en de voorwaarden van <anon> <anon> aan de <anon> zal worden voorgesteld indien hij dat wenst. <anon> antecedenten wat de contractuele verplichting betreft om het risico correct te beschrijven verklaart de <anon> dat: hij ons een exacte en volledige beschrijving van het risico gegeven heeft het verzekerd risico niet door een andere maatschappij is opgezegd hij gedurende de laatste <number> jaar geen schade geleden heeft die verzekerd is in \u00e9\u00e9n van gekozen <anon> hij geen afstand van verhaal tegen verantwoordelijken of <anon> heeft toegestaan. <anon> <anon> <anon> nv koning <anon> <anon> <number> <anon> <anon> <anon> <number> <number> <anon> <anon> bic: <anon> btw: be <number> <anon> <anon> <anon> verzekeringsmaatschappij toegelaten door de nbb <anon> bank van <anon> onder codenummer <anon> alle <anon> <anon> en <anon> te beoefenen <anon> de <anon> <number> <anon> <anon> pagina <number> contract nr <anon> schade <anon> bijzondere clausules met betrekking tot het risico <number> <anon> geografische ligging de toegepaste premie houdt rekening met de geografische ligging van de gewaarborgde goederen. <anon> dekking tegen natuurrampen <anon> antecedenten) bij de <anon> van uw contract hebben we ermee rekening gehouden dat het verzekerde risico gedurende de laatste <number> jaar geen schade heeft geleden door <anon> <anon> rechtsbijstand woning uw contract voorziet de uitgebreide dekking rechtsbijstand woning +. voor de specifieke <anon> met inbegrip van de <anon> verwijzen wij naar de algemene voorwaarden van uw contract. <anon> alleenstaand gebouw de verzekerde inhoud bevindt zich in een alleenstaand gebouw. <anon> diefstal <anon> <number> in afwijking van de bepalingen voorzien in de algemene voorwaarden wordt de <anon> beperkt tot <number> van het verzekerd bedrag <anon> de andere voorziene <anon> blijven evenwel van toepassing. <anon> <anon> <anon> nv koning <anon> <anon> <number> <anon> <anon> <anon> <number> <number> <anon> <anon> bic: <anon> btw: be <number> <anon> <anon> <anon> verzekeringsmaatschappij toegelaten door de nbb <anon> bank van <anon> onder codenummer <anon> alle <anon> <anon> en <anon> te beoefenen <anon> de <anon> <number> <anon> <anon> pagina <number> contract nr <anon> schade <anon> <anon> risico beschermd door een alarminstallatie geplaatst door een gecertificeerde installateur toekenning van een <anon> een vermindering op de premie diefstal wordt toegekend om reden dat de lokalen waarin de verzekerde goederen zich bevinden beschermd worden door een alarminstallatie geplaatst door een gecertificeerde installateur de installateur dient een <anon> af te leveren. worden hiermee gelijkgesteld: alarmsystemen van <anon> of andere alarmsystemen die dezelfde graad van bescherming bieden als de systemen van <anon> gelieve de volgende <anon> in acht te nemen: <number>) een <anon> onderschrijven bij de installateur van het systeem waarbij minstens <number> jaarlijkse controle voorzien wordt alsook een snelle tussenkomst bij <anon> panne van het systeem <number>) <anon> en richtlijnen van de installateur naleven <number>) bij afwezigheid de <anon> niet in de lokalen achter te laten <number>) het systeem activeren van zodra geen enkele verzekerde zich nog in het gebouw bevindt <number>) zelf geen wijzigingen aan de installatie aanbrengen <number>) ons onmiddellijk op de hoogte brengen: a) wanneer het periodiek onderhoud niet meer wordt uitgevoerd door de installateur b) van het toevertrouwen van het onderhoud aan een andere installateur of van de <anon> van het <anon> c) van iedere aan het systeem aangebrachte wijziging <number>) wanneer de installatie niet meer werkt: a) onmiddellijk de installateur oproepen voor het opnieuw in <anon> stellen van de installatie b) de nodige <anon> <anon> treffen tijdens deze periode c) ons verwittigen indien het opnieuw in <anon> stellen niet kan gebeuren binnen de <number> uren. wij zullen onze tussenkomst beperken of zelfs weigeren om tussen te komen in de mate dat het niet <anon> onvoldoende) nemen van deze voorzorgsmaatregelen invloed heeft op het <anon> of de schade. <anon> <anon> <anon> nv koning <anon> <anon> <number> <anon> <anon> <anon> <number> <number> <anon> <anon> bic: <anon> btw: be <number> <anon> <anon> <anon> verzekeringsmaatschappij toegelaten door de nbb <anon> bank van <anon> onder codenummer <anon> alle <anon> <anon> en <anon> te beoefenen <anon> de <anon> <number> <anon> <anon> pagina <number> contract nr <anon> schade <anon> <anon> diefstal afwijking van de <anon> per voorwerp in afwijking van de bepalingen voorzien in de algemene voorwaarden bedraagt de <anon> per voorwerp <money>. de andere voorziene grenzen blijven evenwel van toepassing. <anon> gebruik van het stelsel tot afschaffing van de <anon> voor de inhoud het verzekerd bedrag op inhoud werd vastgesteld op basis van het stelsel tot afschaffing van de <anon> dat wij aan de <anon> voorgesteld hebben. de <anon> wordt dus afgeschaft maar onze vergoeding zal nooit het verzekerd bedrag mogen overschrijden deze bepaling blijft van toepassing ook wanneer later \u00e9\u00e9n bijkomende slaapkamer ingericht wordt. <anon> gebruik van een stelsel tot afschaffing van de <anon> met overschrijding. het verzekerd bedrag voor het gebouw <anon> <anon> werd vastgesteld op basis van het <anon> tot afschaffing van de <anon> met over- <anon> dat wij aan de <anon> voorgesteld hebben. hierbij werd onder andere rekening gehouden met de volgende gegevens die ons meedeelde <number> bewoonbare <anon> <number> <anon> <anon> alleenstaand gebouw <number> <anon> indien \u00e9\u00e9n van deze gegevens of \u00e9\u00e9n van de andere meegedeelde gegevens in het stelsel wijzigt dient ons zo snel mogelijk te verwittigen zodat het contract kan worden aangepast aan deze nieuwe situatie.", "classification": "Policy", "description": "Police", "language": "Dutch"}, {"filename": "factuur 1 Hoedekie 116,23 \u20ac.pdf", "content": "", "classification": "Invoice", "description": "Facture", "language": "Dutch"}], "labels": {"assignment_type": "Unilateral", "case_type": "Property", "sub_case_type": "Fire", "damage_type": "WaterDamage"}}